trustedflow/attestation/generation/__init__.py
trustedflow/attestation/generation/generator.so
trustedflow/attestation/verification/verifier.cpython-310-x86_64-linux-gnu.so
trustedflow_sgx2_generation-0.3.0.dev20240722.dist-info/LICENSE
trustedflow_sgx2_generation-0.3.0.dev20240722.dist-info/METADATA
trustedflow_sgx2_generation-0.3.0.dev20240722.dist-info/WHEEL
trustedflow_sgx2_generation-0.3.0.dev20240722.dist-info/top_level.txt
trustedflow_sgx2_generation-0.3.0.dev20240722.dist-info/RECORD
